sectionate/__init__.py
sectionate/gridutils.py
sectionate/section.py
sectionate/tracers.py
sectionate/transports.py
sectionate/utils.py
sectionate/version.py
sectionate/catalog/Atlantic_transport_arrays.json
sectionate/tests/test_convergent_transport.py
sectionate/tests/test_section.py
sectionate/tests/test_section_class.py
sectionate/tests/test_section_cornercases.py
sectionate/tests/test_utils.py
sectionate-0.3.0.dist-info/METADATA
sectionate-0.3.0.dist-info/WHEEL
sectionate-0.3.0.dist-info/licenses/LICENSE
sectionate-0.3.0.dist-info/RECORD
