Metadata-Version: 2.4
Name: sectionate
Version: 0.3.0
Summary: A package to sample grid-consistent sections from ocean model outputs
Project-URL: Homepage, https://github.com/MOM6-community/sectionate
Project-URL: Bugs/Issues/Features, https://github.com/MOM6-community/sectionate/issues
Project-URL: Sibling package, https://github.com/hdrake/regionate
Author-email: Raphael Dussin <raphael.dussin@gmail.com>, "Henri F. Drake" <hfdrake@uci.edu>
License-File: LICENSE
Classifier: License :: OSI Approved :: GNU General Public License v3 (GPLv3)
Classifier: Operating System :: OS Independent
Classifier: Programming Language :: Python :: 3
Requires-Python: >=3.8
Requires-Dist: dask
Requires-Dist: numba
Requires-Dist: numpy
Requires-Dist: scipy
Requires-Dist: xarray
Requires-Dist: xgcm>=0.9.0
